<annotation>
	<folder></folder>
	<filename>594081c7-23d2-11e8-a6a3-ec086b02610b_jpg.rf.0ed4a6650c5ba1c12492b92bfd6f8152.jpg</filename>
	<path>594081c7-23d2-11e8-a6a3-ec086b02610b_jpg.rf.0ed4a6650c5ba1c12492b92bfd6f8152.jpg</path>
	<source>
		<database>roboflow.com</database>
	</source>
	<size>
		<width>640</width>
		<height>640</height>
		<depth>3</depth>
	</size>
	<segmented>0</segmented>
	<object>
		<name>coyote</name>
		<pose>Unspecified</pose>
		<truncated>0</truncated>
		<difficult>0</difficult>
		<occluded>0</occluded>
		<bndbox>
			<xmin>385</xmin>
			<xmax>575</xmax>
			<ymin>255</ymin>
			<ymax>420</ymax>
		</bndbox>
	</object>
</annotation>
